pytunesmith/__init__.py
pytunesmith/core.py
pytunesmith/effects/__init__.py
pytunesmith/effects/base_effects.py
pytunesmith/effects/effects_pack.py
pytunesmith-0.1.4.dist-info/LICENSE
pytunesmith-0.1.4.dist-info/METADATA
pytunesmith-0.1.4.dist-info/WHEEL
pytunesmith-0.1.4.dist-info/RECORD
